README.md
setup.py
alpha0.egg-info/PKG-INFO
alpha0.egg-info/SOURCES.txt
alpha0.egg-info/dependency_links.txt
alpha0.egg-info/requires.txt
alpha0.egg-info/top_level.txt
yue/__init__.py
yue/test.py
yue/tmp.py
yue/wn.py
yue/wu.py
yue/wy.py